rulesguard/__init__.py
rulesguard/cli.py
rulesguard/config.py
rulesguard/models.py
rulesguard/scanner.py
rulesguard/detectors/__init__.py
rulesguard/detectors/base.py
rulesguard/detectors/entropy.py
rulesguard/detectors/pattern.py
rulesguard/detectors/unicode.py
rulesguard/reporters/__init__.py
rulesguard/reporters/console.py
rulesguard/reporters/json_reporter.py
rulesguard/reporters/sarif.py
rulesguard/templates/__init__.py
rulesguard/templates/rulesguard-audit.yml
rulesguard/templates/rulesguard-gate.yml
rulesguard/templates/rulesguard.yml
rulesguard/templates/rulesguardignore
rulesguard-0.1.6.dist-info/licenses/LICENSE
rulesguard-0.1.6.dist-info/METADATA
rulesguard-0.1.6.dist-info/WHEEL
rulesguard-0.1.6.dist-info/entry_points.txt
rulesguard-0.1.6.dist-info/top_level.txt
rulesguard-0.1.6.dist-info/RECORD
