Metadata-Version: 2.4
Name: rulesguard
Version: 0.1.6
Summary: Security scanner and policy enforcement for AI, IDE, and automation configuration files
Author: RulesGuard Contributors
License-Expression: MIT
Project-URL: Homepage, https://github.com/NOTTIBOY137/RulesGuard
Project-URL: Documentation, https://github.com/NOTTIBOY137/RulesGuard#readme
Project-URL: Repository, https://github.com/NOTTIBOY137/RulesGuard
Project-URL: Issues, https://github.com/NOTTIBOY137/RulesGuard/issues
Keywords: security,scanner,cve,cursor,vscode,configuration
Classifier: Development Status :: 4 - Beta
Classifier: Intended Audience :: Developers
Classifier: Programming Language :: Python :: 3
Classifier: Programming Language :: Python :: 3.9
Classifier: Programming Language :: Python :: 3.10
Classifier: Programming Language :: Python :: 3.11
Classifier: Programming Language :: Python :: 3.12
Classifier: Topic :: Security
Classifier: Topic :: Software Development :: Quality Assurance
Requires-Python: >=3.9
License-File: LICENSE
Requires-Dist: click>=8.1.0
Requires-Dist: rich>=13.7.0
Provides-Extra: dev
Requires-Dist: pytest>=7.4.0; extra == "dev"
Requires-Dist: pytest-cov>=4.1.0; extra == "dev"
Requires-Dist: pytest-mock>=3.12.0; extra == "dev"
Requires-Dist: black>=23.12.0; extra == "dev"
Requires-Dist: ruff>=0.1.9; extra == "dev"
Requires-Dist: mypy>=1.8.0; extra == "dev"
Requires-Dist: types-pyyaml>=6.0.12; extra == "dev"
Dynamic: license-file
